pdz_tool/__init__.py
pdz_tool/base_tool.py
pdz_tool/cli.py
pdz_tool/config.py
pdz_tool/field_parser.py
pdz_tool/pdz24_tool.py
pdz_tool/pdz25_tool.py
pdz_tool/pdz_tool.py
pdz_tool/utils.py
pdz_tool-0.2.5.dist-info/LICENSE
pdz_tool-0.2.5.dist-info/METADATA
pdz_tool-0.2.5.dist-info/WHEEL
pdz_tool-0.2.5.dist-info/entry_points.txt
pdz_tool-0.2.5.dist-info/RECORD
