Metadata-Version: 2.3
Name: pdz-tool
Version: 0.2.5
Summary: A tool for reading and transforming PDZ 24 and PDZ 25 formats
License: MIT
Keywords: pdz,format,transformation
Author: Bruno Ducraux
Author-email: bruno.drx@gmail.com
Requires-Python: >=3.11,<4.0
Classifier: License :: OSI Approved :: MIT License
Classifier: Programming Language :: Python :: 3
Classifier: Programming Language :: Python :: 3.11
Classifier: Programming Language :: Python :: 3.12
Classifier: Programming Language :: Python :: 3.13
Project-URL: Repository, https://github.com/bducraux/pdz-tool
